hello_word_cc1/__init__.py
hello_word_cc1/client.py
hello_world_cc1-0.0.7.dist-info/LICENSE
hello_world_cc1-0.0.7.dist-info/METADATA
hello_world_cc1-0.0.7.dist-info/WHEEL
hello_world_cc1-0.0.7.dist-info/top_level.txt
hello_world_cc1-0.0.7.dist-info/RECORD
